base_folder/__init__.py
base_folder/browser.py
base_folder/definition.py
base_folder/locators.py
hellosmalldemo/__init__.py
hellosmalldemo/hello.py
pyrpabrowserdemo/__init__.py
pyrpabrowserdemo/booking.py
pyrpabrowserdemo/bot_sparebin.py
pyrpabrowserdemo/browser.py
pyrpabrowserdemo/definition.py
pyrpabrowserdemo/run_test_bot.py
pyrpabrowserdemo/test.py
spreadsheetsmalldemo/__init__.py
spreadsheetsmalldemo/browser.py
spreadsheetsmalldemo/definition.py
spreadsheetsmalldemo/sites.py
spreadsheetsmalldemo/test.py
spreadsheetsmalldemo/example/__init__.py
spreadsheetsmalldemo/example/bot.py
spreadsheetsmalldemo/example/locators.py
spreadsheetsmalldemo/rpa/__init__.py
spreadsheetsmalldemo/rpa/ui/__init__.py
spreadsheetsmalldemo/rpa/ui/ui.py
vidstream/__init__.py
vidstream/audio.py
vidstream/streaming.py
vidstreamtestdemo/__init__.py
vidstreamtestdemo/audio.py
vidstreamtestdemo/streaming.py
pyrpabrowserdemo-0.0.5.dist-info/LICENSE
pyrpabrowserdemo-0.0.5.dist-info/METADATA
pyrpabrowserdemo-0.0.5.dist-info/WHEEL
pyrpabrowserdemo-0.0.5.dist-info/top_level.txt
pyrpabrowserdemo-0.0.5.dist-info/RECORD
